verdb/__init__.py
verdb/manager.py
verdb/model.py
verdb/modelset.py
verdb/pytest.py
verdb/repository.py
verdb/section.py
verdb/fields/__init__.py
verdb/fields/collections.py
verdb/fields/field.py
verdb/fields/scalars.py
verdb/fields/special.py
verdb-0.0.5.dist-info/LICENSE
verdb-0.0.5.dist-info/METADATA
verdb-0.0.5.dist-info/WHEEL
verdb-0.0.5.dist-info/entry_points.txt
verdb-0.0.5.dist-info/top_level.txt
verdb-0.0.5.dist-info/RECORD
