Metadata-Version: 2.1
Name: verdb
Version: 0.0.5
Summary: Versioned database backed by git
Home-page: https://github.com/KnowitSolutions/verdb
Author: Andreas Hagen
Author-email: a.hagen@knowit.no
License: MIT
Platform: UNKNOWN
Classifier: Programming Language :: Python :: 3
Classifier: License :: OSI Approved :: MIT License
Classifier: Operating System :: OS Independent
Requires-Dist: ruamel.yaml
Provides-Extra: pytest
Requires-Dist: pytest ; extra == 'pytest'
